nba_py/__init__.py
nba_py/constants.py
nba_py/draftcombine.py
nba_py/game.py
nba_py/league.py
nba_py/player.py
nba_py/shotchart.py
nba_py/team.py
nba_py-0.1a2.dist-info/DESCRIPTION.rst
nba_py-0.1a2.dist-info/METADATA
nba_py-0.1a2.dist-info/metadata.json
nba_py-0.1a2.dist-info/RECORD
nba_py-0.1a2.dist-info/top_level.txt
nba_py-0.1a2.dist-info/WHEEL
