Metadata-Version: 2.0
Name: nba-py
Version: 0.1a2
Summary: A python facing API for stats.nba.com
Home-page: https://github.com/seemethere/nba_py
Author: seemethere
Author-email: seemethere101@gmail.com
License: BSD 3-clause "New" or "Revised License"
Keywords: nba sports data-mining
Platform: UNKNOWN
Classifier: Development Status :: 3 - Alpha
Classifier: Intended Audience :: Developers
Classifier: Intended Audience :: Science/Research
Classifier: License :: OSI Approved :: BSD License
Classifier: Programming Language :: Python :: 2.7
Requires-Dist: requests
Provides-Extra: dev
Requires-Dist: check-manifest; extra == 'dev'
Provides-Extra: test
Requires-Dist: coverage; extra == 'test'
